simo_esphome/__init__.py
simo_esphome/admin.py
simo_esphome/auto_urls.py
simo_esphome/autocomplete_views.py
simo_esphome/base_types.py
simo_esphome/controllers.py
simo_esphome/forms.py
simo_esphome/gateways.py
simo_esphome/models.py
simo_esphome/tasks.py
simo_esphome/todos.py
simo_esphome/utils.py
simo_esphome/views.py
simo_esphome/migrations/0001_initial.py
simo_esphome/migrations/0002_alter_espdevice_firmware_status.py
simo_esphome/migrations/__init__.py
simo_esphome-1.0.1.dist-info/LICENSE.md
simo_esphome-1.0.1.dist-info/METADATA
simo_esphome-1.0.1.dist-info/WHEEL
simo_esphome-1.0.1.dist-info/top_level.txt
simo_esphome-1.0.1.dist-info/RECORD
